[{"calorie":0.0,"count":0,"distance":0.0,"speed":0.0},{"calorie":0.0,"count":0,"distance":0.0,"speed":0.0},{"calorie":0.0,"count":0,"distance":0.0,"speed":0.0},{"calorie":0.0,"count":0,"distance":0.0,"speed":0.0},{"calorie":0.0,"count":0,"distance":0.0,"speed":0.0},{"calorie":0.0,"count":0,"distance":0.0,"speed":0.0},{"calorie":0.0,"count":0,"distance":0.0,"speed":0.0},{"calorie":0.0,"count":0,"distance":0.0,"speed":0.0},{"calorie":0.92,"count":26,"distance":20.5,"speed":5.76536750793457},{"calorie":0.0,"count":0,"distance":0.0,"speed":0.0},{"calorie":0.0,"count":0,"distance":0.0,"speed":0.0},{"calorie":0.0,"count":0,"distance":0.0,"speed":0.0},{"calorie":0.0,"count":0,"distance":0.0,"speed":0.0},{"calorie":0.0,"count":0,"distance":0.0,"speed":0.0},{"calorie":0.0,"count":0,"distance":0.0,"speed":0.0},{"calorie":0.0,"count":0,"distance":0.0,"speed":0.0},{"calorie":0.0,"count":0,"distance":0.0,"speed":0.0},{"calorie":0.0,"count":0,"distance":0.0,"speed":0.0},{"calorie":0.0,"count":0,"distance":0.0,"speed":0.0},{"calorie":0.0,"count":0,"distance":0.0,"speed":0.0},{"calorie":0.0,"count":0,"distance":0.0,"speed":0.0},{"calorie":0.0,"count":0,"distance":0.0,"speed":0.0},{"calorie":0.0,"count":0,"distance":0.0,"speed":0.0},{"calorie":0.0,"count":0,"distance":0.0,"speed":0.0},{"calorie":0.0,"count":0,"distance":0.0,"speed":0.0},{"calorie":0.0,"count":0,"distance":0.0,"speed":0.0},{"calorie":2.2499999999999933,"count":54,"distance":39.19000000000138,"speed":4.805462837219238},{"calorie":5.040000000000044,"count":137,"distance":82.30199999999816,"speed":4.3512797355651855},{"calorie":19.8,"count":554,"distance":395.18000000000006,"speed":4.5067901611328125},{"calorie":0.0,"count":0,"distance":0.0,"speed":0.0},{"calorie":0.0,"count":0,"distance":0.0,"speed":0.0},{"calorie":5.57,"count":164,"distance":123.02,"speed":4.729368686676025},{"calorie":12.059999999999999,"count":313,"distance":217.79000000000002,"speed":4.8414082527160645},{"calorie":1.5499999999999998,"count":45,"distance":32.0,"speed":3.896920919418335},{"calorie":0.0,"count":0,"distance":0.0,"speed":0.0},{"calorie":0.0,"count":0,"distance":0.0,"speed":0.0},{"calorie":0.0,"count":0,"distance":0.0,"speed":0.0},{"calorie":0.0,"count":0,"distance":0.0,"speed":0.0},{"calorie":0.0,"count":0,"distance":0.0,"speed":0.0},{"calorie":0.0,"count":0,"distance":0.0,"speed":0.0},{"calorie":0.0,"count":0,"distance":0.0,"speed":0.0},{"calorie":0.0,"count":0,"distance":0.0,"speed":0.0},{"calorie":0.0,"count":0,"distance":0.0,"speed":0.0},{"calorie":0.0,"count":0,"distance":0.0,"speed":0.0},{"calorie":0.0,"count":0,"distance":0.0,"speed":0.0},{"calorie":0.0,"count":0,"distance":0.0,"speed":0.0},{"calorie":0.0,"count":0,"distance":0.0,"speed":0.0},{"calorie":0.0,"count":0,"distance":0.0,"speed":0.0},{"calorie":0.0,"count":0,"distance":0.0,"speed":0.0},{"calorie":0.83,"count":23,"distance":16.22,"speed":4.0},{"calorie":0.34,"count":11,"distance":9.07,"speed":7.400000095367432},{"calorie":1.8399999999999999,"count":51,"distance":36.86,"speed":4.11187219619751},{"calorie":5.980000000000132,"count":154,"distance":112.4800000000013,"speed":4.587287902832031},{"calorie":1.84,"count":50,"distance":36.3,"speed":4.20534610748291},{"calorie":0.98,"count":26,"distance":18.14,"speed":3.499999761581421},{"calorie":0.0,"count":0,"distance":0.0,"speed":0.0},{"calorie":0.0,"count":0,"distance":0.0,"speed":0.0},{"calorie":0.0,"count":0,"distance":0.0,"speed":0.0},{"calorie":0.8599999821186066,"count":23,"distance":16.139999904632568,"speed":3.5511465072631836},{"calorie":0.41999995708465576,"count":11,"distance":7.749999046325684,"speed":3.3571927547454834},{"calorie":0.0,"count":0,"distance":0.0,"speed":0.0},{"calorie":0.25,"count":7,"distance":5.190000057220459,"speed":4.585275173187256},{"calorie":0.0,"count":0,"distance":0.0,"speed":0.0},{"calorie":4.38,"count":120,"distance":93.6,"speed":5.471901893615723},{"calorie":4.529999999999999,"count":128,"distance":91.72,"speed":3.945932388305664},{"calorie":1.04,"count":32,"distance":24.12,"speed":4.844611644744873},{"calorie":0.0,"count":0,"distance":0.0,"speed":0.0},{"calorie":0.0,"count":0,"distance":0.0,"speed":0.0},{"calorie":0.0,"count":0,"distance":0.0,"speed":0.0},{"calorie":0.0,"count":0,"distance":0.0,"speed":0.0},{"calorie":0.0,"count":0,"distance":0.0,"speed":0.0},{"calorie":1.2300000000000044,"count":36,"distance":29.68099999999889,"speed":6.49278450012207},{"calorie":5.8400000333786375,"count":159,"distance":124.79100057220407,"speed":5.502033710479736},{"calorie":4.159999906420708,"count":112,"distance":83.04000118255615,"speed":4.507970809936523},{"calorie":3.880000014305006,"count":77,"distance":62.9800003814706,"speed":5.782429218292236},{"calorie":6.679999698400638,"count":158,"distance":125.63999897003217,"speed":5.037768840789795},{"calorie":14.699999853372574,"count":393,"distance":291.1999970245361,"speed":4.519376277923584},{"calorie":16.92000009059906,"count":474,"distance":355.9200005340576,"speed":5.086062908172607},{"calorie":19.499999878406527,"count":521,"distance":391.6400039291382,"speed":4.719861030578613},{"calorie":18.73000006079671,"count":483,"distance":358.82999351501485,"speed":4.351053714752197},{"calorie":0.7199999749660492,"count":21,"distance":15.74,"speed":4.482005596160889},{"calorie":0.0,"count":0,"distance":0.0,"speed":0.0},{"calorie":0.0,"count":0,"distance":0.0,"speed":0.0},{"calorie":15.129999160766602,"count":408,"distance":304.48998832702637,"speed":4.48726224899292},{"calorie":13.220000002384168,"count":309,"distance":213.1200016403181,"speed":4.742879867553711},{"calorie":1.4599999487400055,"count":39,"distance":28.010000705718994,"speed":3.7276673316955566},{"calorie":1.6900000274181366,"count":45,"distance":32.77000045776367,"speed":3.923879384994507},{"calorie":0.0,"count":0,"distance":0.0,"speed":0.0},{"calorie":0.0,"count":0,"distance":0.0,"speed":0.0},{"calorie":0.0,"count":0,"distance":0.0,"speed":0.0},{"calorie":0.0,"count":0,"distance":0.0,"speed":0.0},{"calorie":0.25999999046325684,"count":7,"distance":5.079999923706055,"speed":4.014068603515625},{"calorie":2.2999999511241915,"count":62,"distance":44.70999938964844,"speed":3.890620470046997},{"calorie":2.080000002384186,"count":59,"distance":43.589999732971194,"speed":4.460693836212158},{"calorie":0.0,"count":0,"distance":0.0,"speed":0.0},{"calorie":12.499999897480011,"count":340,"distance":251.95999961853028,"speed":4.5504374504089355},{"calorie":3.70999997317791,"count":96,"distance":72.36999998092651,"speed":4.4015889167785645},{"calorie":0.9599999785423279,"count":25,"distance":17.570000171661377,"speed":3.2274985313415527},{"calorie":2.4799999976158005,"count":66,"distance":49.70000038147031,"speed":4.382476329803467},{"calorie":3.7000000023841855,"count":101,"distance":74.10999931335449,"speed":4.201221466064453},{"calorie":8.479999979734448,"count":229,"distance":172.40100003814769,"speed":4.4703826904296875},{"calorie":2.5599999916553635,"count":68,"distance":49.86900038147061,"speed":4.231297492980957},{"calorie":4.240000000000045,"count":108,"distance":84.75100000000063,"speed":5.604431629180908},{"calorie":10.479999895095826,"count":287,"distance":210.12999664306642,"speed":4.454704761505127},{"calorie":3.5899999141693115,"count":91,"distance":67.52999877929688,"speed":4.421271324157715},{"calorie":3.839999990463257,"count":91,"distance":70.82999961853028,"speed":5.188763618469238},{"calorie":1.54,"count":41,"distance":31.909999999999997,"speed":5.549698829650879},{"calorie":1.29,"count":32,"distance":22.72,"speed":3.970633029937744},{"calorie":0.0,"count":0,"distance":0.0,"speed":0.0},{"calorie":0.9799999999999682,"count":28,"distance":20.369000000000234,"speed":4.114339351654053},{"calorie":0.0,"count":0,"distance":0.0,"speed":0.0},{"calorie":0.0,"count":0,"distance":0.0,"speed":0.0},{"calorie":0.6700000166893005,"count":18,"distance":12.920000076293945,"speed":3.499999761581421},{"calorie":0.85,"count":26,"distance":20.48,"speed":5.706984519958496},{"calorie":3.7,"count":104,"distance":75.50999999999999,"speed":4.148199558258057},{"calorie":31.41000000000003,"count":855,"distance":586.7099999999976,"speed":4.5369038581848145},{"calorie":17.769999999999975,"count":505,"distance":369.2199999999988,"speed":4.327917098999023},{"calorie":1.16,"count":31,"distance":22.56,"speed":4.328012466430664},{"calorie":0.43,"count":11,"distance":7.45,"speed":3.0999999046325684},{"calorie":0.0,"count":0,"distance":0.0,"speed":0.0},{"calorie":0.0,"count":0,"distance":0.0,"speed":0.0},{"calorie":0.0,"count":0,"distance":0.0,"speed":0.0},{"calorie":0.0,"count":0,"distance":0.0,"speed":0.0},{"calorie":1.3599999999999044,"count":23,"distance":20.61999999999876,"speed":8.517374992370605},{"calorie":3.4499999034404754,"count":91,"distance":67.72999954223633,"speed":4.404577732086182},{"calorie":19.239999771118164,"count":539,"distance":388.51000213623047,"speed":5.174386978149414},{"calorie":13.259999866485597,"count":332,"distance":233.19000011444092,"speed":4.342892169952393},{"calorie":0.0,"count":0,"distance":0.0,"speed":0.0},{"calorie":0.0,"count":0,"distance":0.0,"speed":0.0},{"calorie":1.9500000000000002,"count":51,"distance":38.620000000000005,"speed":4.5832953453063965},{"calorie":18.800000252723695,"count":504,"distance":378.6699982070923,"speed":5.435202121734619},{"calorie":2.46,"count":45,"distance":35.459999999999994,"speed":5.671079635620117},{"calorie":15.309999995231628,"count":457,"distance":356.0499981689453,"speed":5.547199249267578},{"calorie":3.9899999392032623,"count":109,"distance":80.2199990272522,"speed":4.187675476074219},{"calorie":0.0,"count":0,"distance":0.0,"speed":0.0},{"calorie":0.0,"count":0,"distance":0.0,"speed":0.0},{"calorie":1.9899998903274536,"count":53,"distance":39.1200008392334,"speed":4.132518768310547},{"calorie":1.03,"count":31,"distance":23.73,"speed":5.199999809265137},{"calorie":0.0,"count":0,"distance":0.0,"speed":0.0},{"calorie":2.080000013113022,"count":59,"distance":44.15999979019165,"speed":4.70823335647583},{"calorie":16.93000011205673,"count":509,"distance":395.85000354766845,"speed":5.744858741760254},{"calorie":7.659999942779541,"count":199,"distance":144.66999908447266,"speed":4.2913432121276855},{"calorie":3.5099999749661355,"count":95,"distance":73.44000000000042,"speed":5.1353020668029785},{"calorie":0.0,"count":0,"distance":0.0,"speed":0.0}]